restpite/__init__.py
restpite-0.1.4.dist-info/LICENSE
restpite-0.1.4.dist-info/METADATA
restpite-0.1.4.dist-info/WHEEL
restpite-0.1.4.dist-info/top_level.txt
restpite-0.1.4.dist-info/RECORD
